queueing_tool/__init__.py
queueing_tool/union_find.py
queueing_tool/graph/__init__.py
queueing_tool/graph/graph_functions.py
queueing_tool/graph/graph_generation.py
queueing_tool/graph/graph_preparation.py
queueing_tool/graph/graph_wrapper.py
queueing_tool/network/__init__.py
queueing_tool/network/priority_queue.cp37-win_amd64.pyd
queueing_tool/network/queue_network.py
queueing_tool/queues/__init__.py
queueing_tool/queues/agents.py
queueing_tool/queues/choice.cp37-win_amd64.pyd
queueing_tool/queues/queue_extentions.py
queueing_tool/queues/queue_servers.py
aoi_queueing_tool-1.2.4.dist-info/LICENSE.txt
aoi_queueing_tool-1.2.4.dist-info/METADATA
aoi_queueing_tool-1.2.4.dist-info/WHEEL
aoi_queueing_tool-1.2.4.dist-info/top_level.txt
aoi_queueing_tool-1.2.4.dist-info/RECORD
