Metadata-Version: 2.1
Name: aoi-queueing-tool
Version: 1.2.4
Summary: Queueing network simulator (fork)
Home-page: https://github.com/pprandel/aoi-queueing-tool
Author: Paulo Prandel
Author-email: pauloprandel@hotmail.com
License: MIT
Keywords: queueing theory,queueing,simulation,queueing simulator,queueing network simulation,networks,queueing simulation
Platform: UNKNOWN
Classifier: Development Status :: 4 - Beta
Classifier: Intended Audience :: Science/Research
Classifier: License :: OSI Approved :: MIT License
Classifier: Operating System :: MacOS :: MacOS X
Classifier: Operating System :: Microsoft :: Windows
Classifier: Operating System :: POSIX :: Linux
Classifier: Operating System :: Unix
Classifier: Programming Language :: Python :: 2
Classifier: Programming Language :: Python :: 2.7
Classifier: Programming Language :: Python :: 3
Classifier: Programming Language :: Python :: 3.4
Classifier: Programming Language :: Python :: 3.5
Classifier: Programming Language :: Python :: 3.6
Classifier: Programming Language :: Python :: 3.7
Classifier: Programming Language :: Cython
Classifier: Topic :: Scientific/Engineering :: Information Analysis
Classifier: Topic :: Scientific/Engineering :: Mathematics
License-File: LICENSE.txt
Requires-Dist: networkx (>=1.9)
Requires-Dist: numpy (>=1.9)
